ai3/__init__.py
ai3/_core.cp310-win_amd64.pyd
ai3/_core.pyi
ai3/_version.py
ai3/csrc/adaptiveavgpool2d/direct_plain.cpp
ai3/csrc/ai3.cpp
ai3/csrc/ai3.hpp
ai3/csrc/algos.hpp
ai3/csrc/avgpool2d/direct_plain.cpp
ai3/csrc/context.hpp
ai3/csrc/conv2d/direct_plain.cpp
ai3/csrc/conv2d/direct_sycl.cpp
ai3/csrc/conv2d/exec_cudnn.hpp
ai3/csrc/conv2d/gemm_cudnn.cpp
ai3/csrc/conv2d/gemm_plain.cpp
ai3/csrc/conv2d/guess_cudnn.cpp
ai3/csrc/conv2d/guess_plain.cpp
ai3/csrc/conv2d/implicit_gemm_cudnn.cpp
ai3/csrc/conv2d/implicit_gemm_plain.cpp
ai3/csrc/conv2d/implicit_precomp_gemm_cudnn.cpp
ai3/csrc/conv2d/implicit_precomp_gemm_plain.cpp
ai3/csrc/conv2d/metal_metal.mm
ai3/csrc/conv2d/metal_plain.cpp
ai3/csrc/conv2d/mps_mps.mm
ai3/csrc/conv2d/mps_plain.cpp
ai3/csrc/conv2d/smm_plain.cpp
ai3/csrc/conv2d/smm_sycl.cpp
ai3/csrc/conv2d/winograd_cudnn.cpp
ai3/csrc/conv2d/winograd_plain.cpp
ai3/csrc/cublas_utils.hpp
ai3/csrc/cudnn_utils.hpp
ai3/csrc/flatten/direct_plain.cpp
ai3/csrc/linear/gemm_cublas.cpp
ai3/csrc/linear/gemm_plain.cpp
ai3/csrc/maxpool2d/direct_plain.cpp
ai3/csrc/relu/direct_plain.cpp
ai3/csrc/tensor.hpp
ai3/csrc/utils.hpp
ai3/custom/adaptiveavgpool2d.hpp
ai3/custom/avgpool2d.hpp
ai3/custom/conv2d.hpp
ai3/custom/flatten.hpp
ai3/custom/linear.hpp
ai3/custom/maxpool2d.hpp
ai3/custom/relu.hpp
ai3/errors.py
ai3/layers.py
ai3/swap_torch.py
ai3/tensor.py
ai3/utils.py
aithree-0.1.0.dist-info/METADATA
aithree-0.1.0.dist-info/WHEEL
aithree-0.1.0.dist-info/licenses/LICENSE
aithree-0.1.0.dist-info/RECORD
