Metadata-Version: 2.1
Name: aithree
Version: 0.1.0
Summary: Enables Algorithmic Selection and Customization in Deep Neural Networks
Author: Timothy Cronin
Classifier: Topic :: Scientific/Engineering :: Artificial Intelligence
Classifier: Topic :: Software Development :: Libraries
Classifier: License :: OSI Approved :: Apache Software License
Classifier: Intended Audience :: Developers
Classifier: Intended Audience :: Science/Research
Classifier: Programming Language :: C++
Classifier: Programming Language :: Python
Requires-Python: >=3.8
Provides-Extra: dev
Provides-Extra: format
Provides-Extra: doc
Requires-Dist: numpy; extra == "dev"
Requires-Dist: torch; extra == "dev"
Requires-Dist: torchvision; extra == "dev"
Requires-Dist: autopep8; extra == "format"
Requires-Dist: sphinx; extra == "doc"
Requires-Dist: breathe; extra == "doc"
Requires-Dist: pydata-sphinx-theme; extra == "doc"
